flows_e2e_tests/__init__.py
flows_e2e_tests/cli/__init__.py
flows_e2e_tests/cli/main.py
flows_e2e_tests/config/__init__.py
flows_e2e_tests/config/config.py
flows_e2e_tests/config/custom.py
flows_e2e_tests/config/settings.toml
flows_e2e_tests/pyproject.toml
flows_e2e_tests/scenarios/consent_required/__init__.py
flows_e2e_tests/scenarios/consent_required/conftest.py
flows_e2e_tests/scenarios/consent_required/test_consent_required.py
flows_e2e_tests/scenarios/flow_lifecycle/__init__.py
flows_e2e_tests/scenarios/flow_lifecycle/conftest.py
flows_e2e_tests/scenarios/flow_lifecycle/test_deletes.py
flows_e2e_tests/scenarios/flow_lifecycle/test_deploy.py
flows_e2e_tests/scenarios/flow_lifecycle/test_gets.py
flows_e2e_tests/scenarios/flow_lifecycle/test_runs.py
flows_e2e_tests/scenarios/flow_lifecycle/test_updates.py
flows_e2e_tests/scenarios/load_testing/__init__.py
flows_e2e_tests/scenarios/load_testing/main.py
flows_e2e_tests/scenarios/load_testing/users.py
flows_e2e_tests/scenarios/soft_delete/__init__.py
flows_e2e_tests/scenarios/soft_delete/conftest.py
flows_e2e_tests/scenarios/soft_delete/test_flow_soft_delete.py
flows_e2e_tests/scenarios/soft_delete/test_run_soft_delete.py
flows_e2e_tests/utils/__init__.py
flows_e2e_tests/utils/auth.py
flows_e2e_tests/utils/flows.py
flows_e2e_tests/utils/models.py
flows_e2e_tests/utils/providers.py
flows_e2e_tests/utils/scopes.py
flows_e2e_tests-0.1.12.dist-info/entry_points.txt
flows_e2e_tests-0.1.12.dist-info/WHEEL
flows_e2e_tests-0.1.12.dist-info/METADATA
flows_e2e_tests-0.1.12.dist-info/RECORD
