Metadata-Version: 2.1
Name: flows-e2e-tests
Version: 0.1.12
Summary: 
Author: Uriel Mandujano
Author-email: uriel@globus.org
Requires-Python: >=3.9,<4.0
Classifier: Programming Language :: Python :: 3
Classifier: Programming Language :: Python :: 3.10
Classifier: Programming Language :: Python :: 3.9
Requires-Dist: dynaconf (>=3.1.4,<4.0.0)
Requires-Dist: globus-automate-client (>=0.12.0,<0.13.0)
Requires-Dist: locust (>=2.2.3,<3.0.0)
Requires-Dist: pydantic (>=1.8.2,<2.0.0)
Requires-Dist: pytest (>=6.2.4,<7.0.0)
Requires-Dist: pytest-xdist (>=2.3.0,<3.0.0)
Requires-Dist: structlog (>=21.1.0,<22.0.0)
Requires-Dist: typer[all] (<0.4.0)
